{
  "version": 1,
  "schema": [
    {
      "name": "hello-request",
      "namespace": "example",
      "compact": false,
      "flagsPosition": 3,
      "fields": [
        {
          "name": "text",
          "required": true,
          "type": "string",
          "version": 1
        },
        {
          "name": "from",
          "required": true,
          "type": "string",
          "version": 1
        },
        {
          "name": "age",
          "required": true,
          "type": "int",
          "version": 1
        },
        {
          "name": "happy",
          "required": false,
          "type": "bool",
          "version": 1
        },
        {
          "name": "dogs",
          "required": true,
          "array": true,
          "type": "string",
          "version": 1
        }
      ]
    },
    {
      "name": "hello-response",
      "namespace": "example",
      "compact": false,
      "flagsPosition": 0,
      "fields": [
        {
          "name": "reply",
          "type": "string",
          "version": 1
        }
      ]
    }
  ]
}
